mdeng/__init__.py
mdeng-1.0.5.dist-info/LICENSE
mdeng-1.0.5.dist-info/METADATA
mdeng-1.0.5.dist-info/WHEEL
mdeng-1.0.5.dist-info/top_level.txt
mdeng-1.0.5.dist-info/RECORD
