Metadata-Version: 2.1
Name: mdeng
Version: 1.0.5
Summary: A package for a Python Markdown parser engine
Home-page: https://github.com/youhengzhou/mdeng
Author: YouHeng Zhou
Author-email: youhengzhou@cmail.carleton.ca
Project-URL: Bug Tracker, https://github.com/youhengzhou/mdeng/issues
Classifier: Programming Language :: Python :: 3
Classifier: License :: OSI Approved :: MIT License
Classifier: Operating System :: OS Independent
Requires-Python: >=3.6
License-File: LICENSE
